tkforms/__init__.py
tkforms/gunaui2.test1.py
tkforms/gunaui2.test2.py
tkforms/gunaui2.test3.py
tkforms/metro.example1.py
tkforms/metro.test1.py
tkforms/metro.test2.py
tkforms/toolbar.py
tkforms/gunaui2/Guna.UI2.dll
tkforms/gunaui2/GunaUI2.py
tkforms/gunaui2/__init__.py
tkforms/hzhcontrols/HZHControls.py
tkforms/hzhcontrols/HZH_Controls.dll
tkforms/hzhcontrols/__init__.py
tkforms/materialskin/MaterialSkin.dll
tkforms/materialskin/MaterialUI.py
tkforms/materialskin/__init__.py
tkforms/metroframework/MetroFramework.Design.dll
tkforms/metroframework/MetroFramework.Fonts.dll
tkforms/metroframework/MetroFramework.dll
tkforms/metroframework/MetroUI.py
tkforms/metroframework/__init__.py
tkforms/telerik/Telerik.py
tkforms/telerik/__init__.py
tkforms-2.1.0.dist-info/METADATA
tkforms-2.1.0.dist-info/WHEEL
tkforms-2.1.0.dist-info/top_level.txt
tkforms-2.1.0.dist-info/RECORD
